omniblack/py_indexes/__init__.py
omniblack.py_indexes-0.1.0.dist-info/LICENSE.txt
omniblack.py_indexes-0.1.0.dist-info/METADATA
omniblack.py_indexes-0.1.0.dist-info/WHEEL
omniblack.py_indexes-0.1.0.dist-info/top_level.txt
omniblack.py_indexes-0.1.0.dist-info/RECORD
