Metadata-Version: 2.1
Name: omniblack.py-indexes
Version: 0.1.0
Author-email: Terry Patterson <Terryp@wegrok.net>
License: 
Project-URL: Homepage, https://gitlab.com/terryp/terry/-/tree/next/lib/py_indexes
Project-URL: Repository, https://gitlab.com/terryp/terry.git
License-File: LICENSE.txt
Requires-Dist: frozendict ~=2.4
Requires-Dist: requests ~=2.31
Requires-Dist: packaging ~=23.2
Requires-Dist: requests-cache ~=1.1
Requires-Dist: pyxdg ~=0.27
